dssl/__init__.py
dssl-0.0.1.dist-info/METADATA
dssl-0.0.1.dist-info/WHEEL
dssl-0.0.1.dist-info/top_level.txt
dssl-0.0.1.dist-info/RECORD
