Metadata-Version: 2.4
Name: dssl
Version: 0.0.1
Summary: Distributed Situation Semantics Library (DSSL)
Author-email: Adrian Brasoveanu <abrsvn@gmail.com>
License: Apache-2.0
Project-URL: Homepage, https://github.com/abrsvn/dssl
Project-URL: Repository, https://github.com/abrsvn/dssl
Project-URL: Bug Tracker, https://github.com/abrsvn/dssl/issues
Classifier: Development Status :: 3 - Alpha
Classifier: Intended Audience :: Science/Research
Classifier: Operating System :: OS Independent
Classifier: Programming Language :: Python :: 3
Classifier: Programming Language :: Python :: 3.12
Classifier: Topic :: Scientific/Engineering :: Artificial Intelligence
Classifier: Topic :: Text Processing :: Linguistic
Classifier: Topic :: Scientific/Engineering :: Mathematics
Classifier: Topic :: Software Development :: Libraries :: Python Modules
Requires-Python: >=3.12
Requires-Dist: matplotlib
Requires-Dist: numpy>=1.15
Requires-Dist: pandas>=1.1.2
Requires-Dist: packaging
Requires-Dist: pyparsing
Requires-Dist: requests
Requires-Dist: torch>=1.11
